jupyter_ai_persona_manager/__init__.py
jupyter_ai_persona_manager/_version.py
jupyter_ai_persona_manager/base_persona.py
jupyter_ai_persona_manager/directories.py
jupyter_ai_persona_manager/extension.py
jupyter_ai_persona_manager/handlers.py
jupyter_ai_persona_manager/persona_awareness.py
jupyter_ai_persona_manager/persona_manager.py
jupyter_ai_persona_manager/tests/__init__.py
jupyter_ai_persona_manager/tests/conftest.py
jupyter_ai_persona_manager/tests/test_directories.py
jupyter_ai_persona_manager/tests/test_extension.py
jupyter_ai_persona_manager/tests/test_handlers.py
jupyter_ai_persona_manager/tests/test_persona_manager.py
jupyter_ai_persona_manager-0.0.4.data/data/etc/jupyter/jupyter_server_config.d/jupyter_ai_persona_manager.json
jupyter_ai_persona_manager-0.0.4.data/data/share/jupyter/labextensions/@jupyter-ai/persona-manager/package.json
jupyter_ai_persona_manager-0.0.4.data/data/share/jupyter/labextensions/@jupyter-ai/persona-manager/static/509.2ad10a57495919c61175.js
jupyter_ai_persona_manager-0.0.4.data/data/share/jupyter/labextensions/@jupyter-ai/persona-manager/static/728.2358ccda7aa7c48f0821.js
jupyter_ai_persona_manager-0.0.4.data/data/share/jupyter/labextensions/@jupyter-ai/persona-manager/static/remoteEntry.473434a09113ac8fc67d.js
jupyter_ai_persona_manager-0.0.4.data/data/share/jupyter/labextensions/@jupyter-ai/persona-manager/static/style.js
jupyter_ai_persona_manager-0.0.4.data/data/share/jupyter/labextensions/@jupyter-ai/persona-manager/static/third-party-licenses.json
jupyter_ai_persona_manager-0.0.4.data/data/share/jupyter/labextensions/@jupyter-ai/persona-manager/install.json
jupyter_ai_persona_manager-0.0.4.dist-info/METADATA
jupyter_ai_persona_manager-0.0.4.dist-info/WHEEL
jupyter_ai_persona_manager-0.0.4.dist-info/licenses/LICENSE
jupyter_ai_persona_manager-0.0.4.dist-info/RECORD
