Metadata-Version: 2.4
Name: jupyter_ai_persona_manager
Version: 0.0.4
Summary: The core manager & registry for AI personas in Jupyter AI
Project-URL: Homepage, https://github.com/jupyter-ai-contrib/jupyter-ai-persona-manager
Project-URL: Bug Tracker, https://github.com/jupyter-ai-contrib/jupyter-ai-persona-manager/issues
Project-URL: Repository, https://github.com/jupyter-ai-contrib/jupyter-ai-persona-manager.git
Author-email: Project Jupyter <jupyter@googlegroups.com>
License: BSD 3-Clause License
License-File: LICENSE
Keywords: jupyter,jupyterlab,jupyterlab-extension
Classifier: Framework :: Jupyter
Classifier: Framework :: Jupyter :: JupyterLab
Classifier: Framework :: Jupyter :: JupyterLab :: 4
Classifier: Framework :: Jupyter :: JupyterLab :: Extensions
Classifier: Framework :: Jupyter :: JupyterLab :: Extensions :: Prebuilt
Classifier: License :: OSI Approved :: BSD License
Classifier: Programming Language :: Python
Classifier: Programming Language :: Python :: 3
Classifier: Programming Language :: Python :: 3.9
Classifier: Programming Language :: Python :: 3.10
Classifier: Programming Language :: Python :: 3.11
Classifier: Programming Language :: Python :: 3.12
Classifier: Programming Language :: Python :: 3.13
Requires-Python: >=3.9
Requires-Dist: importlib-metadata>=4.0.0
Requires-Dist: jupyter-ai-router>=0.0.1
Requires-Dist: jupyter-server-fileid>=0.9.0
Requires-Dist: jupyter-server<3,>=2.4.0
Requires-Dist: jupyterlab-chat>=0.16.0
Requires-Dist: pycrdt>=0.10.0
Requires-Dist: pydantic>=2.0.0
Provides-Extra: test
Requires-Dist: coverage; extra == 'test'
Requires-Dist: pytest; extra == 'test'
Requires-Dist: pytest-asyncio; extra == 'test'
Requires-Dist: pytest-cov; extra == 'test'
Requires-Dist: pytest-jupyter[server]>=0.6.0; extra == 'test'
